<?xml version = '1.0' encoding = 'UTF-8'?>
<Relation class="oracle.dbtools.crest.model.design.logical.Relation" name="FK_PRODUTO_SOLICITACAO_PRODUTO" directorySegmentName="seg_0" id="E40F50A2-97A1-3F4A-5425-B8FF461EC964">
<createdBy>Fonse</createdBy>
<createdTime>2023-05-31 00:28:48 UTC</createdTime>
<ownerDesignName>Modelo-Logico-Food-Share</ownerDesignName>
<engineerTo>
<item key="FD5619F3-A476-4AAE-BBCE-45439047CB9C" value="true"/>
</engineerTo>
<sourcePk>21C32B1E-7B31-06AD-7C8E-BC0E90015FC0</sourcePk>
<identifying>false</identifying>
<optionalSource>true</optionalSource>
<optionalTarget>false</optionalTarget>
<sourceCardinality>1</sourceCardinality>
<sourceEntity>6BDD762F-639C-54D8-5480-A6F0AFFF8198</sourceEntity>
<targetCardinalityString>*</targetCardinalityString>
<targetEntity>FDD274A9-6FD8-886F-758F-6521704200D1</targetEntity>
<transferable>true</transferable>
<deleteRule>NO ACTION</deleteRule>
</Relation>
